{"cameraMode":{"drawMode":0,"name":"Shaded","section":"Shading Mode"},"sceneLighting":true,"audioPlay":false,"sceneViewState":{"m_AlwaysRefresh":false,"showFog":true,"showSkybox":true,"showFlares":true,"showImageEffects":true,"showParticleSystems":true,"showVisualEffectGraphs":true,"m_FxEnabled":true},"in2DMode":false,"pivot":{"x":8.934468269348145,"y":9.3473539352417,"z":-20.114103317260743},"rotation":{"x":-0.2514297664165497,"y":0.40411779284477236,"z":-0.11656096577644348,"w":-0.8717159628868103},"size":10.0,"orthographic":false}